polygons_share_edge.cpython-310-x86_64-linux-gnu.so
polygons_share_edge-1.2.dist-info/top_level.txt
polygons_share_edge-1.2.dist-info/RECORD
polygons_share_edge-1.2.dist-info/WHEEL
polygons_share_edge-1.2.dist-info/METADATA
polygons_share_edge-1.2.dist-info/LICENSE
